Workbook

Sheet Sheet3
A2: Sales by Region and Segment
A3: Sum of Sales | B3: Column Labels
A4: Row Labels | B4: Consumer | C4: Corporate | D4: Home Office | E4: Grand Total
A5: East | B5: 4198.19 | C5: 15907.19 | D5: 8738.98 | E5: 28844.36
A6: North | B6: 40524.29 | D6: 48348.28 | E6: 88872.57
A7: South | B7: 68729.97 | C7: 37500.49 | D7: 23567.78 | E7: 129798.24
A8: West | B8: 4146.22 | C8: 4905.85 | D8: 5182.1 | E8: 14234.17
A9: Grand Total | B9: 117598.67 | C9: 58313.53 | D9: 85837.14 | E9: 261749.34

Sheet Sheet2
A2: Profit bt Category and Region
A3: Count of Profit | B3: Column Labels
A4: Row Labels | B4: East | C4: North | D4: South | E4: West | F4: (blank) | G4: Grand Total
A5: Furniture | B5: 5 | C5: 12 | D5: 17 | E5: 2 | G5: 36
A6: Office Supplies | B6: 3 | C6: 11 | D6: 14 | E6: 4 | G6: 32
A7: Technology | B7: 7 | C7: 10 | D7: 14 | E7: 1 | G7: 32
A8: (blank)
A9: Grand Total | B9: 15 | C9: 33 | D9: 45 | E9: 7 | G9: 100

Sheet Sheet4
A2: Monthly Sales Trend
A3: Row Labels | B3: Count of Sales
A4: (blank)
A5: Jan | B5: 8
A6: Feb | B6: 7
A7: Mar | B7: 10
A8: Apr | B8: 10
A9: May | B9: 11
A10: Jun | B10: 10
A11: Jul | B11: 10
A12: Aug | B12: 7
A13: Sep | B13: 6
A14: Oct | B14: 11
A15: Nov | B15: 5
A16: Dec | B16: 5
A17: Grand Total | B17: 100

Sheet Sheet6
A2: Top 10 Customers
A3: Row Labels | B3: Count of Sales
A4: Amit Mishra | B4: 5
A5: Ananya Agarwal | B5: 4
A6: Ananya Mishra | B6: 3
A7: Ananya Singh | B7: 4
A8: Ananya Verma | B8: 3
A9: Karan Singh | B9: 3
A10: Neha Verma | B10: 5
A11: Priya Singh | B11: 3
A12: Rahul Agarwal | B12: 4
A13: Sneha Jain | B13: 7
A14: Sneha Verma | B14: 5
A15: Vidushi Jain | B15: 3
... A20: Grand Total | B20: 65

Sheet orders_dataset
A1: Order_ID | B1: Order_Date | C1: Customer_ID | D1: Product_Category | E1: Sales | F1: Quantity | G1: Profit | H1: Discount | I1: Region | J1: Profit Margin | K1: Segment | L1: Customer_name | M1: Profit Margin_new
A2: 1001 | B2: 45729 | C2: 5048 | D2: Furniture | E2: 3233.19 | F2: 1 | G2: 359.6 | H2: 0.1 | I2: =VLOOKUP(C2, customer_dataset!A:C, 3, FALSE) -> North | J2: =G2/E2 -> 0.11122143 | K2: =VLOOKUP(C2, customer_dataset!A:D, 4, FALSE) -> Home Office | L2: =VLOOKUP(C2, customer_dataset!A:B, 2, FALSE) -> Vivaan Yadav | M2: =IF(F2=0, 0, G2/F2) -> 359.6
A3: 1002 | B3: 45674 | C3: 5002 | D3: Furniture | E3: 3415.83 | F3: 9 | G3: 675.05 | H3: 0 | I3: =VLOOKUP(C3, customer_dataset!A:C, 3, FALSE) -> South | J3: =G3/E3 -> 0.197624 | K3: =VLOOKUP(C3, customer_dataset!A:D, 4, FALSE) -> Consumer | L3: =VLOOKUP(C3, customer_dataset!A:B, 2, FALSE) -> Priya Singh | M3: =IF(F3=0, 0, G3/F3) -> 75.005556
A4: 1003 | B4: 45759 | C4: 5046 | D4: Office Supplies | E4: 1171.33 | F4: 9 | G4: 66.34 | H4: 0.2 | I4: =VLOOKUP(C4, customer_dataset!A:C, 3, FALSE) -> West | J4: =G4/E4 -> 0.056636473 | K4: =VLOOKUP(C4, customer_dataset!A:D, 4, FALSE) -> Home Office | L4: =VLOOKUP(C4, customer_dataset!A:B, 2, FALSE) -> Sneha Yadav | M4: =IF(F4=0, 0, G4/F4) -> 7.3711111
A5: 1004 | B5: 45800 | C5: 5001 | D5: Furniture | E5: 3536.49 | F5: 7 | G5: 573.98 | H5: 0.05 | I5: =VLOOKUP(C5, customer_dataset!A:C, 3, FALSE) -> North | J5: =G5/E5 -> 0.16230217 | K5: =VLOOKUP(C5, customer_dataset!A:D, 4, FALSE) -> Home Office | L5: =VLOOKUP(C5, customer_dataset!A:B, 2, FALSE) -> Sneha Verma | M5: =IF(F5=0, 0, G5/F5) -> 81.997143
A6: 1005 | B6: 45830 | C6: 5007 | D6: Furniture | E6: 3520.88 | F6: 6 | G6: 312.9 | H6: 0.1 | I6: =VLOOKUP(C6, customer_dataset!A:C, 3, FALSE) -> North | J6: =G6/E6 -> 0.088869828 | K6: =VLOOKUP(C6, customer_dataset!A:D, 4, FALSE) -> Consumer | L6: =VLOOKUP(C6, customer_dataset!A:B, 2, FALSE) -> Amit Mishra | M6: =IF(F6=0, 0, G6/F6) -> 52.15
A7: 1006 | B7: 45680 | C7: 5047 | D7: Technology | E7: 1961.64 | F7: 6 | G7: 394.16 | H7: 0.1 | I7: =VLOOKUP(C7, customer_dataset!A:C, 3, FALSE) -> South | J7: =G7/E7 -> 0.20093391 | K7: =VLOOKUP(C7, customer_dataset!A:D, 4, FALSE) -> Consumer | L7: =VLOOKUP(C7, customer_dataset!A:B, 2, FALSE) -> Neha Verma | M7: =IF(F7=0, 0, G7/F7) -> 65.693333
A8: 1007 | B8: 45979 | C8: 5040 | D8: Technology | E8: 2727.52 | F8: 7 | G8: 512.8 | H8: 0 | I8: =VLOOKUP(C8, customer_dataset!A:C, 3, FALSE) -> South | J8: =G8/E8 -> 0.18800962 | K8: =VLOOKUP(C8, customer_dataset!A:D, 4, FALSE) -> Consumer | L8: =VLOOKUP(C8, customer_dataset!A:B, 2, FALSE) -> Vidushi Mishra | M8: =IF(F8=0, 0, G8/F8) -> 73.257143
A9: 1008 | B9: 45806 | C9: 5006 | D9: Furniture | E9: 2929.03 | F9: 2 | G9: 630.67 | H9: 0 | I9: =VLOOKUP(C9, customer_dataset!A:C, 3, FALSE) -> South | J9: =G9/E9 -> 0.21531702 | K9: =VLOOKUP(C9, customer_dataset!A:D, 4, FALSE) -> Corporate | L9: =VLOOKUP(C9, customer_dataset!A:B, 2, FALSE) -> Ananya Agarwal | M9: =IF(F9=0, 0, G9/F9) -> 315.335
A10: 1009 | B10: 45844 | C10: 5011 | D10: Technology | E10: 4345.77 | F10: 7 | G10: 709.89 | H10: 0.1 | I10: =VLOOKUP(C10, customer_dataset!A:C, 3, FALSE) -> North | J10: =G10/E10 -> 0.16335195 | K10: =VLOOKUP(C10, customer_dataset!A:D, 4, FALSE) -> Home Office | L10: =VLOOKUP(C10, customer_dataset!A:B, 2, FALSE) -> Vidushi Mishra | M10: =IF(F10=0, 0, G10/F10) -> 101.41286
A11: 1010 | B11: 45745 | C11: 5035 | D11: Office Supplies | E11: 1840.83 | F11: 5 | G11: 372.37 | H11: 0 | I11: =VLOOKUP(C11, customer_dataset!A:C, 3, FALSE) -> North | J11: =G11/E11 -> 0.20228375 | K11: =VLOOKUP(C11, customer_dataset!A:D, 4, FALSE) -> Home Office | L11: =VLOOKUP(C11, customer_dataset!A:B, 2, FALSE) -> Aditya Jain | M11: =IF(F11=0, 0, G11/F11) -> 74.474
A12: 1011 | B12: 45985 | C12: 5045 | D12: Office Supplies | E12: 1299.57 | F12: 8 | G12: 152.68 | H12: 0.15 | I12: =VLOOKUP(C12, customer_dataset!A:C, 3, FALSE) -> East | J12: =G12/E12 -> 0.11748501 | K12: =VLOOKUP(C12, customer_dataset!A:D, 4, FALSE) -> Corporate | L12: =VLOOKUP(C12, customer_dataset!A:B, 2, FALSE) -> Karan Singh | M12: =IF(F12=0, 0, G12/F12) -> 19.085
A13: 1012 | B13: 45674 | C13: 5021 | D13: Technology | E13: 1176.11 | F13: 6 | G13: 126.15 | H13: 0 | I13: =VLOOKUP(C13, customer_dataset!A:C, 3, FALSE) -> South | J13: =G13/E13 -> 0.10726038 | K13: =VLOOKUP(C13, customer_dataset!A:D, 4, FALSE) -> Home Office | L13: =VLOOKUP(C13, customer_dataset!A:B, 2, FALSE) -> Riya Mishra | M13: =IF(F13=0, 0, G13/F13) -> 21.025
... A101: 1100 | B101: 45908 | C101: 5007 | D101: Technology | E101: 437.89 | F101: 6 | G101: 114.9 | H101: 0 | I101: =VLOOKUP(C101, customer_dataset!A:C, 3, FALSE) -> North | J101: =G101/E101 -> 0.26239467 | K101: =VLOOKUP(C101, customer_dataset!A:D, 4, FALSE) -> Consumer | L101: =VLOOKUP(C101, customer_dataset!A:B, 2, FALSE) -> Amit Mishra | M101: =IF(F101=0, 0, G101/F101) -> 19.15

Sheet customer_dataset
A1: Customer_ID | B1: Customer_Name | C1: Region | D1: Segment
A2: 5001 | B2: Sneha Verma | C2: North | D2: Home Office
A3: 5002 | B3: Priya Singh | C3: South | D3: Consumer
A4: 5003 | B4: Karan Verma | C4: North | D4: Home Office
A5: 5004 | B5: Riya Sharma | C5: North | D5: Consumer
A6: 5005 | B6: Ananya Singh | C6: North | D6: Home Office
A7: 5006 | B7: Ananya Agarwal | C7: South | D7: Corporate
A8: 5007 | B8: Amit Mishra | C8: North | D8: Consumer
A9: 5008 | B9: Karan Agarwal | C9: East | D9: Corporate
A10: 5009 | B10: Aditya Singh | C10: East | D10: Consumer
A11: 5010 | B11: Vivaan Agarwal | C11: North | D11: Corporate
A12: 5011 | B12: Vidushi Mishra | C12: North | D12: Home Office
A13: 5012 | B13: Neha Verma | C13: West | D13: Consumer
... A101: 5100 | B101: Karan Verma | C101: West | D101: Consumer
